paper2remarkable/__init__.py
paper2remarkable/__main__.py
paper2remarkable/__version__.py
paper2remarkable/crop.py
paper2remarkable/exceptions.py
paper2remarkable/log.py
paper2remarkable/pdf_ops.py
paper2remarkable/ui.py
paper2remarkable/utils.py
paper2remarkable/providers/__init__.py
paper2remarkable/providers/_base.py
paper2remarkable/providers/_info.py
paper2remarkable/providers/acl.py
paper2remarkable/providers/acm.py
paper2remarkable/providers/arxiv.py
paper2remarkable/providers/citeseerx.py
paper2remarkable/providers/cvf.py
paper2remarkable/providers/diva.py
paper2remarkable/providers/eccc.py
paper2remarkable/providers/html.py
paper2remarkable/providers/iacr.py
paper2remarkable/providers/jmlr.py
paper2remarkable/providers/local.py
paper2remarkable/providers/nature.py
paper2remarkable/providers/nber.py
paper2remarkable/providers/neurips.py
paper2remarkable/providers/openreview.py
paper2remarkable/providers/pdf_url.py
paper2remarkable/providers/pmlr.py
paper2remarkable/providers/pubmed.py
paper2remarkable/providers/sagepub.py
paper2remarkable/providers/science_direct.py
paper2remarkable/providers/semantic_scholar.py
paper2remarkable/providers/springer.py
paper2remarkable/providers/tandfonline.py
paper2remarkable-0.9.14.data/data/man/man1/p2r.1
paper2remarkable-0.9.14.dist-info/LICENSE
paper2remarkable-0.9.14.dist-info/METADATA
paper2remarkable-0.9.14.dist-info/WHEEL
paper2remarkable-0.9.14.dist-info/entry_points.txt
paper2remarkable-0.9.14.dist-info/top_level.txt
paper2remarkable-0.9.14.dist-info/RECORD
