Metadata-Version: 2.1
Name: paper2remarkable
Version: 0.9.14
Summary: Easily download an academic paper and send it to the reMarkable
Home-page: https://github.com/GjjvdBurg/paper2remarkable
Author: Gertjan van den Burg
Author-email: gertjanvandenburg@gmail.com
License: MIT
Classifier: License :: OSI Approved :: MIT License
Classifier: Programming Language :: Python
Classifier: Programming Language :: Python :: 3
Classifier: Programming Language :: Python :: 3.9
Classifier: Programming Language :: Python :: 3.10
Classifier: Programming Language :: Python :: 3.11
Classifier: Programming Language :: Python :: 3.12
Classifier: Programming Language :: Python :: Implementation :: CPython
Classifier: Programming Language :: Python :: Implementation :: PyPy
Classifier: Intended Audience :: Education
Classifier: Intended Audience :: Science/Research
Classifier: Topic :: Education
Classifier: Topic :: Scientific/Engineering
Classifier: Topic :: Utilities
Requires-Python: >=3.9.0
License-File: LICENSE
Requires-Dist: beautifulsoup4>=4.8
Requires-Dist: html2text>=2020.1.16
Requires-Dist: lxml_html_clean>=0.1.1
Requires-Dist: markdown>=3.1.1
Requires-Dist: pdfplumber>=0.11
Requires-Dist: pikepdf>=2.9.0
Requires-Dist: pycryptodome
Requires-Dist: pyyaml>=5.1
Requires-Dist: readability-lxml>=0.7.1
Requires-Dist: regex>=2018.11
Requires-Dist: requests>=2.21
Requires-Dist: titlecase>=0.12
Requires-Dist: unidecode>=1.1
Requires-Dist: validators>=0.34
Requires-Dist: weasyprint>=51
Provides-Extra: full
Requires-Dist: readabilipy; extra == "full"
Provides-Extra: docs
Provides-Extra: test
Requires-Dist: green; extra == "test"
Requires-Dist: readabilipy; extra == "test"
Provides-Extra: dev
Requires-Dist: green; extra == "dev"
Requires-Dist: readabilipy; extra == "dev"
